hashidtools/__init__.py
hashidtools/exceptions.py
hashidtools/fields.py
hashidtools/interfaces.py
hashidtools/types.py
hashidtools-1.0.2.dist-info/LICENSE.txt
hashidtools-1.0.2.dist-info/METADATA
hashidtools-1.0.2.dist-info/RECORD
hashidtools-1.0.2.dist-info/WHEEL
hashidtools-1.0.2.dist-info/top_level.txt
tests/__init__.py
tests/test_fields.py
tests/test_types.py
