Metadata-Version: 2.1
Name: hashidtools
Version: 1.0.2
Summary: HashID based ID Toolkit.
Home-page: https://github.com/joeblackwaslike/hashidtools
Author: Joe Black
Author-email: me@joeblack.nyc
Maintainer: Joe Black
Maintainer-email: me@joeblack.nyc
License: MIT
Download-URL: https://github.com/joeblackwaslike/hashidtools/tarball/v1.0.2
Keywords: hashid,id-generation,distributed,zodb,database,datamodels
Platform: UNKNOWN
Classifier: Development Status :: 4 - Beta
Classifier: Intended Audience :: Developers
Classifier: Operating System :: OS Independent
Classifier: Natural Language :: English
Classifier: License :: OSI Approved :: MIT License
Classifier: Programming Language :: Python :: 3
Classifier: Programming Language :: Python :: 3.6
Classifier: Programming Language :: Python :: 3 :: Only
Classifier: Topic :: Internet :: WWW/HTTP
Classifier: Topic :: Software Development
Classifier: Topic :: Utilities
Classifier: Topic :: Software Development :: Libraries :: Python Modules
Requires-Dist: zope.component (>=4.4.1)
Requires-Dist: zope.configuration (>=4.1.0)
Requires-Dist: zope.interface (>=4.5.0)
Requires-Dist: zope.schema (>=4.5.0)
Requires-Dist: zope.event (>=4.3.0)
Requires-Dist: zope.security (>=4.2.2)
Requires-Dist: zope.intid (>=4.3.0)
Requires-Dist: zc.intid (>=2.0.0)
Requires-Dist: BTrees (>=4.5.0)
Requires-Dist: attrs (>=18.1.0)
Requires-Dist: hashids (>=1.2.0)
